s3manage/.buckets.py.swp
s3manage/.cli.py.swp
s3manage/.index.py.swp
s3manage/__init__.py
s3manage/__main__.py
s3manage/buckets.py
s3manage/cli.py
s3manage/index.py
s3manage-0.3.0.dist-info/DESCRIPTION.rst
s3manage-0.3.0.dist-info/METADATA
s3manage-0.3.0.dist-info/RECORD
s3manage-0.3.0.dist-info/WHEEL
s3manage-0.3.0.dist-info/entry_points.txt
s3manage-0.3.0.dist-info/metadata.json
s3manage-0.3.0.dist-info/top_level.txt
