Metadata-Version: 2.0
Name: s3manage
Version: 0.3.0
Summary: Utilities to help manage S3 buckets
Home-page: https://github.com/greg-hellings/s3manage
Author: Gregory Hellings
Author-email: greg.hellings@gmail.com
License: BSD
Keywords: aws,s3
Platform: UNKNOWN
Classifier: Development Status :: 5 - Production/Stable
Classifier: Intended Audience :: Developers
Classifier: License :: OSI Approved :: BSD License
Classifier: Operating System :: Unix
Classifier: Operating System :: POSIX
Classifier: Operating System :: Microsoft :: Windows
Classifier: Programming Language :: Python
Classifier: Programming Language :: Python :: 2.7
Classifier: Programming Language :: Python :: 3
Classifier: Programming Language :: Python :: 3.3
Classifier: Programming Language :: Python :: 3.4
Classifier: Programming Language :: Python :: 3.5
Classifier: Programming Language :: Python :: 3.6
Classifier: Programming Language :: Python :: Implementation :: CPython
Classifier: Programming Language :: Python :: Implementation :: PyPy
Classifier: Topic :: Utilities
Requires-Dist: boto3
Requires-Dist: aws-shell
Requires-Dist: munch
Requires-Dist: six
Requires-Dist: future
Requires-Dist: humanfriendly
